README.md
setup.py
ares/__init__.py
ares/core.py
ares.egg-info/PKG-INFO
ares.egg-info/SOURCES.txt
ares.egg-info/dependency_links.txt
ares.egg-info/top_level.txt