Metadata-Version: 2.1
Name: ares
Version: 0.6.0
Summary: Python wrapper around https://cve.circl.lu.
Home-page: https://github.com/barnumbirr/ares
Author: Martin Simon
Author-email: me@martinsimon.me
License: Apache v2.0 License
Project-URL: Buy me a coffee, https://github.com/barnumbirr/ares#buy-me-a-coffee
Project-URL: Bug Reports, https://github.com/barnumbirr/ares/issues
Keywords: CVE,cybersecurity,vulnerability,circl.lu
Platform: UNKNOWN
Classifier: License :: OSI Approved :: Apache Software License
Classifier: Development Status :: 5 - Production/Stable
Classifier: Intended Audience :: Developers
Classifier: Programming Language :: Python
Classifier: Programming Language :: Python :: 2.7
Classifier: Programming Language :: Python :: 3.7
Classifier: Topic :: Software Development :: Libraries :: Python Modules
